{
  "trackers": [
    {
      "type": "unknown",
      "url": "https://eu.posthog.com/static/array.js"
    },
    {
      "type": "unknown",
      "url": "https://eu.posthog.com/e/?ip=1&_=1704591720723&ver=1.96.0"
    },
    {
      "type": "unknown",
      "url": "https://eu.posthog.com/decide/?v=3&ip=1&_=1704591720730&ver=1.96.0"
    }
  ],
  "cookies": [
    {
      "name": "_pk_ses.50.a290",
      "value": "1",
      "domain": ".longuevieauxobjets.ademe.fr",
      "path": "/",
      "expires": 1704593520,
      "size": 16,
      "httpOnly": false,
      "secure": true,
      "session": false,
      "sameSite": "None",
      "sameParty": false,
      "sourceScheme": "Secure",
      "sourcePort": 443
    },
    {
      "name": "_pk_id.50.a290",
      "value": "20d6b4e063c90324.1704591721.",
      "domain": ".longuevieauxobjets.ademe.fr",
      "path": "/",
      "expires": 1738546921,
      "size": 42,
      "httpOnly": false,
      "secure": true,
      "session": false,
      "sameSite": "None",
      "sameParty": false,
      "sourceScheme": "Secure",
      "sourcePort": 443
    },
    {
      "name": "ph_phc_SGbYOrenShCMKJOQYyl62se9ZqCHntjTlzgKNhrKnzm_posthog",
      "value": "%7B%22distinct_id%22%3A%22018ce195-810d-78b4-bffe-59f984f0129d%22%2C%22%24sesid%22%3A%5B1704591720720%2C%22018ce195-8110-73ca-9e7d-c72f33a2154d%22%2C1704591720720%5D%7D",
      "domain": ".ademe.fr",
      "path": "/",
      "expires": 1736127720,
      "size": 226,
      "httpOnly": false,
      "secure": true,
      "session": false,
      "sameSite": "Lax",
      "sameParty": false,
      "sourceScheme": "Secure",
      "sourcePort": 443
    },
    {
      "name": "sc-sticky-session",
      "value": "e3r6H8Cih6PhBV6bt2NPOFLuKFseFA/Cux9PLe5ZWG13bWNClKbqXMJ6J7Pr6p7xukDP6Ab6akaN9pPqUnWnmw==",
      "domain": "longuevieauxobjets.ademe.fr",
      "path": "/",
      "expires": 1704678120.725098,
      "size": 105,
      "httpOnly": true,
      "secure": true,
      "session": false,
      "sameSite": "None",
      "sameParty": false,
      "sourceScheme": "Secure",
      "sourcePort": 443
    }
  ],
  "headers": {
    "content-encoding": "gzip",
    "content-type": "text/html; charset=utf-8",
    "cross-origin-opener-policy": "same-origin",
    "date": "Sun, 07 Jan 2024 01:41:59 GMT",
    "referrer-policy": "same-origin",
    "set-cookie": "sc-sticky-session=e3r6H8Cih6PhBV6bt2NPOFLuKFseFA/Cux9PLe5ZWG13bWNClKbqXMJ6J7Pr6p7xukDP6Ab6akaN9pPqUnWnmw==; Expires=Mon, 08-Jan-24 01:41:59 GMT; Max-Age=86400; Path=/; Secure; HttpOnly; SameSite=None",
    "strict-transport-security": "max-age=31536000",
    "x-content-type-options": "nosniff",
    "x-frame-options": "ALLOWALL",
    "x-request-id": "27c5daa3-1a0e-4615-b30f-b16aaa65628e"
  },
  "endpoints": [
    {
      "hostname": "longuevieauxobjets.ademe.fr",
      "ip": "109.232.236.90",
      "geoip": {
        "continent": {
          "code": "EU",
          "geoname_id": 6255148,
          "names": {
            "de": "Europa",
            "en": "Europe",
            "es": "Europa",
            "fr": "Europe",
            "ja": "ヨーロッパ",
            "pt-BR": "Europa",
            "ru": "Европа",
            "zh-CN": "欧洲"
          }
        },
        "country": {
          "geoname_id": 3017382,
          "is_in_european_union": true,
          "iso_code": "FR",
          "names": {
            "de": "Frankreich",
            "en": "France",
            "es": "Francia",
            "fr": "France",
            "ja": "フランス共和国",
            "pt-BR": "França",
            "ru": "Франция",
            "zh-CN": "法国"
          }
        },
        "location": {
          "accuracy_radius": 500,
          "latitude": 48.8582,
          "longitude": 2.3387,
          "time_zone": "Europe/Paris"
        },
        "registered_country": {
          "geoname_id": 3017382,
          "is_in_european_union": true,
          "iso_code": "FR",
          "names": {
            "de": "Frankreich",
            "en": "France",
            "es": "Francia",
            "fr": "France",
            "ja": "フランス共和国",
            "pt-BR": "França",
            "ru": "Франция",
            "zh-CN": "法国"
          }
        }
      }
    },
    {
      "hostname": "eu.posthog.com",
      "ip": "18.67.65.107",
      "geoip": {
        "continent": {
          "code": "NA",
          "geoname_id": 6255149,
          "names": {
            "de": "Nordamerika",
            "en": "North America",
            "es": "Norteamérica",
            "fr": "Amérique du Nord",
            "ja": "北アメリカ",
            "pt-BR": "América do Norte",
            "ru": "Северная Америка",
            "zh-CN": "北美洲"
          }
        },
        "country": {
          "geoname_id": 6252001,
          "iso_code": "US",
          "names": {
            "de": "Vereinigte Staaten",
            "en": "United States",
            "es": "Estados Unidos",
            "fr": "États Unis",
            "ja": "アメリカ",
            "pt-BR": "EUA",
            "ru": "США",
            "zh-CN": "美国"
          }
        },
        "location": {
          "accuracy_radius": 1000,
          "latitude": 37.751,
          "longitude": -97.822,
          "time_zone": "America/Chicago"
        },
        "registered_country": {
          "geoname_id": 6252001,
          "iso_code": "US",
          "names": {
            "de": "Vereinigte Staaten",
            "en": "United States",
            "es": "Estados Unidos",
            "fr": "États Unis",
            "ja": "アメリカ",
            "pt-BR": "EUA",
            "ru": "США",
            "zh-CN": "美国"
          }
        }
      }
    }
  ]
}
