{
  "trackers": [
    {
      "type": "unknown",
      "url": "https://s3.fr-par.scw.cloud/qfdmo-interface/images/shutterstock_1271755384.width-1200.jpg?X-Amz-Algorithm=AWS4-HMAC-SHA256&X-Amz-Credential=SCWZB4T14FAQ8K9SHDEK%2F20260405%2Ffr-par%2Fs3%2Faws4_request&X-Amz-Date=20260405T025611Z&X-Amz-Expires=3600&X-Amz-SignedHeaders=host&X-Amz-Signature=35204ab441a7dccf29b1ec1fde2a4d8da140c78986a3b9ea45f665383a5752e8"
    },
    {
      "type": "unknown",
      "url": "https://s3.fr-par.scw.cloud/qfdmo-interface/images/shutterstock_2448065421.width-1200.jpg?X-Amz-Algorithm=AWS4-HMAC-SHA256&X-Amz-Credential=SCWZB4T14FAQ8K9SHDEK%2F20260405%2Ffr-par%2Fs3%2Faws4_request&X-Amz-Date=20260405T025611Z&X-Amz-Expires=3600&X-Amz-SignedHeaders=host&X-Amz-Signature=14ed437f15e231eb9b6c5ec7c7a1e2f360c955f684dc7293beb28fec88d13261"
    },
    {
      "type": "unknown",
      "url": "https://s3.fr-par.scw.cloud/qfdmo-interface/images/shutterstock_2101625077.width-1200.jpg?X-Amz-Algorithm=AWS4-HMAC-SHA256&X-Amz-Credential=SCWZB4T14FAQ8K9SHDEK%2F20260405%2Ffr-par%2Fs3%2Faws4_request&X-Amz-Date=20260405T025611Z&X-Amz-Expires=3600&X-Amz-SignedHeaders=host&X-Amz-Signature=c30ac5221ec1b8db99f1010fa98335c5422bb811bf03fb5974c5a62c1a7a6b58"
    },
    {
      "type": "unknown",
      "url": "https://s3.fr-par.scw.cloud/qfdmo-interface/images/shutterstock_2286653167.width-1200.jpg?X-Amz-Algorithm=AWS4-HMAC-SHA256&X-Amz-Credential=SCWZB4T14FAQ8K9SHDEK%2F20260405%2Ffr-par%2Fs3%2Faws4_request&X-Amz-Date=20260405T025611Z&X-Amz-Expires=3600&X-Amz-SignedHeaders=host&X-Amz-Signature=6eecd91bd1ba43702f4ca138b4bb7de3dd5f837d68f1c635d290394fad9a070c"
    },
    {
      "type": "unknown",
      "url": "https://s3.fr-par.scw.cloud/qfdmo-interface/images/img_snippet_bonus_rep.width-1200.svg?X-Amz-Algorithm=AWS4-HMAC-SHA256&X-Amz-Credential=SCWZB4T14FAQ8K9SHDEK%2F20260405%2Ffr-par%2Fs3%2Faws4_request&X-Amz-Date=20260405T025611Z&X-Amz-Expires=3600&X-Amz-SignedHeaders=host&X-Amz-Signature=55c9b61f5e6eac2ed1a5eda58de15bcf2ba6ae9e8d886673ad36c740e526efbf"
    },
    {
      "type": "unknown",
      "url": "https://s3.fr-par.scw.cloud/qfdmo-interface/images/search.width-80.svg?X-Amz-Algorithm=AWS4-HMAC-SHA256&X-Amz-Credential=SCWZB4T14FAQ8K9SHDEK%2F20260405%2Ffr-par%2Fs3%2Faws4_request&X-Amz-Date=20260405T025611Z&X-Amz-Expires=3600&X-Amz-SignedHeaders=host&X-Amz-Signature=358d4c5855b2cd91d627177ce39c3fda6a0f47abc6b759a998dc3a6fb604e015"
    },
    {
      "type": "unknown",
      "url": "https://s3.fr-par.scw.cloud/qfdmo-interface/images/location-overseas-france.width-80.svg?X-Amz-Algorithm=AWS4-HMAC-SHA256&X-Amz-Credential=SCWZB4T14FAQ8K9SHDEK%2F20260405%2Ffr-par%2Fs3%2Faws4_request&X-Amz-Date=20260405T025611Z&X-Amz-Expires=3600&X-Amz-SignedHeaders=host&X-Amz-Signature=a73d89761de894bdfe57c8f99891f62ca37e2ccafcdcd1c4237b6834f68cc65f"
    },
    {
      "type": "unknown",
      "url": "https://s3.fr-par.scw.cloud/qfdmo-interface/images/innovation.width-80.svg?X-Amz-Algorithm=AWS4-HMAC-SHA256&X-Amz-Credential=SCWZB4T14FAQ8K9SHDEK%2F20260405%2Ffr-par%2Fs3%2Faws4_request&X-Amz-Date=20260405T025611Z&X-Amz-Expires=3600&X-Amz-SignedHeaders=host&X-Amz-Signature=e5afe7dbfba8e1b220ca6cf99872d2204016188d665b5d2948a002a32a6e0e70"
    },
    {
      "type": "unknown",
      "url": "https://s3.fr-par.scw.cloud/qfdmo-interface/images/environment.width-80.svg?X-Amz-Algorithm=AWS4-HMAC-SHA256&X-Amz-Credential=SCWZB4T14FAQ8K9SHDEK%2F20260405%2Ffr-par%2Fs3%2Faws4_request&X-Amz-Date=20260405T025611Z&X-Amz-Expires=3600&X-Amz-SignedHeaders=host&X-Amz-Signature=4debadd73b647f8d9ed6734547e399b82bf61e75dcc8a7df2fc9e2dd80dcf1d2"
    },
    {
      "type": "unknown",
      "url": "https://s3.fr-par.scw.cloud/qfdmo-interface/images/logo-agir-ademe.width-1200.svg?X-Amz-Algorithm=AWS4-HMAC-SHA256&X-Amz-Credential=SCWZB4T14FAQ8K9SHDEK%2F20260405%2Ffr-par%2Fs3%2Faws4_request&X-Amz-Date=20260405T025611Z&X-Amz-Expires=3600&X-Amz-SignedHeaders=host&X-Amz-Signature=f0ba56ffa11ce0edb8b6fe40cd368c089fd352874e585b2cf487e4dee29d17f4"
    },
    {
      "type": "unknown",
      "url": "https://s3.fr-par.scw.cloud/qfdmo-interface/logos/Logo_ADEME.png?X-Amz-Algorithm=AWS4-HMAC-SHA256&X-Amz-Credential=SCWZB4T14FAQ8K9SHDEK%2F20260405%2Ffr-par%2Fs3%2Faws4_request&X-Amz-Date=20260405T025611Z&X-Amz-Expires=3600&X-Amz-SignedHeaders=host&X-Amz-Signature=064850c80d4c5feacbe859f56811e94bcec444f2e80958ea87913a6f53db9bc0"
    },
    {
      "type": "unknown",
      "url": "https://eu-assets.i.posthog.com/array/phc_CyGuWk8OiY0aUEc7b2BmZnQavKKHLndHZWqLIWQpTgt/config.js"
    },
    {
      "type": "unknown",
      "url": "https://eu.posthog.com/flags/?v=2&config=true&ip=0&_=1775358039160&ver=1.345.2&compression=base64"
    },
    {
      "type": "unknown",
      "url": "https://eu-assets.i.posthog.com/static/dead-clicks-autocapture.js?v=1.345.2"
    },
    {
      "type": "unknown",
      "url": "https://eu-assets.i.posthog.com/static/surveys.js?v=1.345.2"
    },
    {
      "type": "unknown",
      "url": "https://eu.i.posthog.com/api/surveys/?token=phc_CyGuWk8OiY0aUEc7b2BmZnQavKKHLndHZWqLIWQpTgt&ip=0&_=1775358039914&ver=1.345.2"
    }
  ],
  "cookies": [
    {
      "name": "_pk_id.82.b332",
      "value": "29eb4ca0fc94a0c7.1775358040.",
      "domain": "quefairedemesdechets.ademe.fr",
      "path": "/",
      "expires": 1809313240,
      "size": 42,
      "httpOnly": false,
      "secure": false,
      "session": false,
      "sameSite": "Lax",
      "priority": "Medium",
      "sourceScheme": "Secure",
      "sameParty": false
    },
    {
      "name": "sc-sticky-session",
      "value": "WmwA/5yGo8xDHYlVgzohK7LMHmegEC27RRZdNwnirHlsvQ2lVgI7/rLOI4hDo6Qn0uMy/ATty8y7psJl7c061Q==",
      "domain": "quefairedemesdechets.ademe.fr",
      "path": "/",
      "expires": 1775444439.07343,
      "size": 105,
      "httpOnly": true,
      "secure": true,
      "session": false,
      "sameSite": "None",
      "priority": "Medium",
      "sourceScheme": "Secure",
      "sameParty": false
    },
    {
      "name": "_pk_ses.82.b332",
      "value": "1",
      "domain": "quefairedemesdechets.ademe.fr",
      "path": "/",
      "expires": 1775359839,
      "size": 16,
      "httpOnly": false,
      "secure": false,
      "session": false,
      "sameSite": "Lax",
      "priority": "Medium",
      "sourceScheme": "Secure",
      "sameParty": false
    }
  ],
  "headers": {
    "cache-control": "max-age=900",
    "content-encoding": "gzip",
    "content-language": "en",
    "content-type": "text/html; charset=utf-8",
    "cross-origin-opener-policy": "same-origin",
    "date": "Sun, 05 Apr 2026 03:00:38 GMT",
    "referrer-policy": "strict-origin-when-cross-origin",
    "set-cookie": "sc-sticky-session=WmwA/5yGo8xDHYlVgzohK7LMHmegEC27RRZdNwnirHlsvQ2lVgI7/rLOI4hDo6Qn0uMy/ATty8y7psJl7c061Q==; Expires=Mon, 06-Apr-26 03:00:38 GMT; Max-Age=86400; Path=/; Secure; HttpOnly; SameSite=None",
    "strict-transport-security": "max-age=31536000",
    "vary": "Accept-Encoding\nlogged-in, iframe, sec-fetch-dest, Accept-Language, Cookie, origin",
    "x-cache-status": "HIT",
    "x-content-type-options": "nosniff",
    "x-frame-options": "ALLOWALL",
    "x-request-id": "3d5d1e31-fc61-4aec-b02c-af787c2b0c79"
  },
  "endpoints": [
    {
      "hostname": "quefairedemesdechets.ademe.fr",
      "ip": "109.232.233.130",
      "geoip": {
        "continent": {
          "code": "EU",
          "geoname_id": 6255148,
          "names": {
            "de": "Europa",
            "en": "Europe",
            "es": "Europa",
            "fr": "Europe",
            "ja": "ヨーロッパ",
            "pt-BR": "Europa",
            "ru": "Европа",
            "zh-CN": "欧洲"
          }
        },
        "country": {
          "geoname_id": 3017382,
          "is_in_european_union": true,
          "iso_code": "FR",
          "names": {
            "de": "Frankreich",
            "en": "France",
            "es": "Francia",
            "fr": "France",
            "ja": "フランス共和国",
            "pt-BR": "França",
            "ru": "Франция",
            "zh-CN": "法国"
          }
        },
        "location": {
          "accuracy_radius": 500,
          "latitude": 48.8582,
          "longitude": 2.3387,
          "time_zone": "Europe/Paris"
        },
        "registered_country": {
          "geoname_id": 3017382,
          "is_in_european_union": true,
          "iso_code": "FR",
          "names": {
            "de": "Frankreich",
            "en": "France",
            "es": "Francia",
            "fr": "France",
            "ja": "フランス共和国",
            "pt-BR": "França",
            "ru": "Франция",
            "zh-CN": "法国"
          }
        }
      }
    },
    {
      "hostname": "s3.fr-par.scw.cloud",
      "ip": "51.159.62.20",
      "geoip": {
        "city": {
          "geoname_id": 2988507,
          "names": {
            "de": "Paris",
            "en": "Paris",
            "es": "París",
            "fr": "Paris",
            "ja": "パリ",
            "pt-BR": "Paris",
            "ru": "Париж",
            "zh-CN": "巴黎"
          }
        },
        "continent": {
          "code": "EU",
          "geoname_id": 6255148,
          "names": {
            "de": "Europa",
            "en": "Europe",
            "es": "Europa",
            "fr": "Europe",
            "ja": "ヨーロッパ",
            "pt-BR": "Europa",
            "ru": "Европа",
            "zh-CN": "欧洲"
          }
        },
        "country": {
          "geoname_id": 3017382,
          "is_in_european_union": true,
          "iso_code": "FR",
          "names": {
            "de": "Frankreich",
            "en": "France",
            "es": "Francia",
            "fr": "France",
            "ja": "フランス共和国",
            "pt-BR": "França",
            "ru": "Франция",
            "zh-CN": "法国"
          }
        },
        "location": {
          "accuracy_radius": 20,
          "latitude": 48.8558,
          "longitude": 2.3494,
          "time_zone": "Europe/Paris"
        },
        "postal": {
          "code": "75001"
        },
        "registered_country": {
          "geoname_id": 3017382,
          "is_in_european_union": true,
          "iso_code": "FR",
          "names": {
            "de": "Frankreich",
            "en": "France",
            "es": "Francia",
            "fr": "France",
            "ja": "フランス共和国",
            "pt-BR": "França",
            "ru": "Франция",
            "zh-CN": "法国"
          }
        },
        "subdivisions": [
          {
            "geoname_id": 3012874,
            "iso_code": "IDF",
            "names": {
              "de": "Île-de-France",
              "en": "Île-de-France",
              "es": "Isla de Francia",
              "fr": "Île-de-France",
              "ja": "イル・ド・フランス",
              "pt-BR": "Ilha de França",
              "ru": "Иль-де-Франс",
              "zh-CN": "法兰西岛"
            }
          },
          {
            "geoname_id": 2968815,
            "iso_code": "75",
            "names": {
              "de": "Département Paris",
              "en": "Paris Department",
              "es": "Departamento de París",
              "fr": "Département de Paris"
            }
          }
        ]
      }
    },
    {
      "hostname": "eu-assets.i.posthog.com",
      "ip": "104.20.17.167",
      "geoip": {
        "registered_country": {
          "geoname_id": 6252001,
          "iso_code": "US",
          "names": {
            "de": "USA",
            "en": "United States",
            "es": "Estados Unidos",
            "fr": "États-Unis",
            "ja": "アメリカ",
            "pt-BR": "EUA",
            "ru": "США",
            "zh-CN": "美国"
          }
        }
      }
    },
    {
      "hostname": "eu.posthog.com",
      "ip": "18.184.170.153",
      "geoip": {
        "city": {
          "geoname_id": 2925533,
          "names": {
            "de": "Frankfurt am Main",
            "en": "Frankfurt am Main",
            "es": "Francfort",
            "fr": "Francfort-sur-le-Main",
            "ja": "フランクフルト・アム・マイン",
            "pt-BR": "Frankfurt am Main",
            "ru": "Франкфурт",
            "zh-CN": "法兰克福"
          }
        },
        "continent": {
          "code": "EU",
          "geoname_id": 6255148,
          "names": {
            "de": "Europa",
            "en": "Europe",
            "es": "Europa",
            "fr": "Europe",
            "ja": "ヨーロッパ",
            "pt-BR": "Europa",
            "ru": "Европа",
            "zh-CN": "欧洲"
          }
        },
        "country": {
          "geoname_id": 2921044,
          "is_in_european_union": true,
          "iso_code": "DE",
          "names": {
            "de": "Deutschland",
            "en": "Germany",
            "es": "Alemania",
            "fr": "Allemagne",
            "ja": "ドイツ連邦共和国",
            "pt-BR": "Alemanha",
            "ru": "ФРГ",
            "zh-CN": "德国"
          }
        },
        "location": {
          "accuracy_radius": 20,
          "latitude": 50.1169,
          "longitude": 8.6837,
          "time_zone": "Europe/Berlin"
        },
        "postal": {
          "code": "60313"
        },
        "registered_country": {
          "geoname_id": 6252001,
          "iso_code": "US",
          "names": {
            "de": "USA",
            "en": "United States",
            "es": "Estados Unidos",
            "fr": "États-Unis",
            "ja": "アメリカ",
            "pt-BR": "EUA",
            "ru": "США",
            "zh-CN": "美国"
          }
        },
        "subdivisions": [
          {
            "geoname_id": 2905330,
            "iso_code": "HE",
            "names": {
              "de": "Hessen",
              "en": "Hesse",
              "es": "Hessen",
              "fr": "Hesse",
              "ja": "ヘッセン州",
              "pt-BR": "Hesse",
              "ru": "Гессен",
              "zh-CN": "黑森州"
            }
          }
        ]
      }
    },
    {
      "hostname": "eu.i.posthog.com",
      "ip": "3.125.203.202",
      "geoip": {
        "city": {
          "geoname_id": 2925533,
          "names": {
            "de": "Frankfurt am Main",
            "en": "Frankfurt am Main",
            "es": "Francfort",
            "fr": "Francfort-sur-le-Main",
            "ja": "フランクフルト・アム・マイン",
            "pt-BR": "Frankfurt am Main",
            "ru": "Франкфурт",
            "zh-CN": "法兰克福"
          }
        },
        "continent": {
          "code": "EU",
          "geoname_id": 6255148,
          "names": {
            "de": "Europa",
            "en": "Europe",
            "es": "Europa",
            "fr": "Europe",
            "ja": "ヨーロッパ",
            "pt-BR": "Europa",
            "ru": "Европа",
            "zh-CN": "欧洲"
          }
        },
        "country": {
          "geoname_id": 2921044,
          "is_in_european_union": true,
          "iso_code": "DE",
          "names": {
            "de": "Deutschland",
            "en": "Germany",
            "es": "Alemania",
            "fr": "Allemagne",
            "ja": "ドイツ連邦共和国",
            "pt-BR": "Alemanha",
            "ru": "ФРГ",
            "zh-CN": "德国"
          }
        },
        "location": {
          "accuracy_radius": 20,
          "latitude": 50.1169,
          "longitude": 8.6837,
          "time_zone": "Europe/Berlin"
        },
        "postal": {
          "code": "60313"
        },
        "registered_country": {
          "geoname_id": 6252001,
          "iso_code": "US",
          "names": {
            "de": "USA",
            "en": "United States",
            "es": "Estados Unidos",
            "fr": "États-Unis",
            "ja": "アメリカ",
            "pt-BR": "EUA",
            "ru": "США",
            "zh-CN": "美国"
          }
        },
        "subdivisions": [
          {
            "geoname_id": 2905330,
            "iso_code": "HE",
            "names": {
              "de": "Hessen",
              "en": "Hesse",
              "es": "Hessen",
              "fr": "Hesse",
              "ja": "ヘッセン州",
              "pt-BR": "Hesse",
              "ru": "Гессен",
              "zh-CN": "黑森州"
            }
          }
        ]
      }
    }
  ]
}
